pksuid/__init__.py
pksuid/pksuid.py
pksuid-1.1.1.dist-info/LICENSE.txt
pksuid-1.1.1.dist-info/WHEEL
pksuid-1.1.1.dist-info/METADATA
pksuid-1.1.1.dist-info/RECORD
