Metadata-Version: 2.1
Name: pksuid
Version: 1.1.1
Summary: Python package for generating prefixed ksuids.
Home-page: https://github.com/sashahilton00/python-pksuid
License: MIT
Keywords: uid,uuid,ksuid,pksuid
Author: Sasha Hilton
Author-email: sashahilton00@gmail.com
Requires-Python: >=3.6,<4.0
Classifier: License :: OSI Approved :: MIT License
Classifier: Programming Language :: Python :: 3
Classifier: Programming Language :: Python :: 3.10
Classifier: Programming Language :: Python :: 3.6
Classifier: Programming Language :: Python :: 3.7
Classifier: Programming Language :: Python :: 3.8
Classifier: Programming Language :: Python :: 3.9
Requires-Dist: pybase62 (==0.4.3)
Project-URL: Repository, https://github.com/sashahilton00/python-pksuid
